{"airship":{"bgm":{"name":"Ship3","pan":0,"pitch":100,"volume":90},"characterIndex":3,"characterName":"Vehicle","startMapId":0,"startX":0,"startY":0},"armorTypes":["","一般防具","魔法防具","輕型防具","重型防具","小型盾","大型盾"],"attackMotions":[{"type":0,"weaponImageId":0},{"type":1,"weaponImageId":1},{"type":1,"weaponImageId":2},{"type":1,"weaponImageId":3},{"type":1,"weaponImageId":4},{"type":1,"weaponImageId":5},{"type":1,"weaponImageId":6},{"type":2,"weaponImageId":7},{"type":2,"weaponImageId":8},{"type":2,"weaponImageId":9},{"type":0,"weaponImageId":10},{"type":0,"weaponImageId":11},{"type":0,"weaponImageId":12}],"battleBgm":{"name":"CS_NormalBattleBGM","pan":0,"pitch":100,"volume":50},"battleback1Name":"forest_earth2","battleback2Name":"forest2","battlerHue":0,"battlerName":"Dragon","boat":{"bgm":{"name":"Ship1","pan":0,"pitch":100,"volume":90},"characterIndex":0,"characterName":"Vehicle","startMapId":0,"startX":0,"startY":0},"currencyUnit":"C","defeatMe":{"name":"Defeat1","pan":0,"pitch":100,"volume":90},"editMapId":4,"elements":["","物理","火焰","冰","雷","水","土","風","光","暗"],"equipTypes":["","武器","身體","頭部","特殊裝備1","特殊装備2","特殊装備3","特殊装備4"],"gameTitle":"【GORPG】Chris Survival汉化版","gameoverMe":{"name":"Gameover1","pan":0,"pitch":100,"volume":90},"locale":"ja_JP","magicSkills":[1],"menuCommands":[true,true,true,true,true,true],"optDisplayTp":true,"optDrawTitle":false,"optExtraExp":false,"optFloorDeath":false,"optFollowers":false,"optSideView":false,"optSlipDeath":false,"optTransparent":true,"partyMembers":[1,2,3,4],"ship":{"bgm":{"name":"Ship2","pan":0,"pitch":100,"volume":90},"characterIndex":1,"characterName":"Vehicle","startMapId":0,"startX":0,"startY":0},"skillTypes":["","必殺技","淫技","特殊行動"],"sounds":[{"name":"Cursor1","pan":0,"pitch":100,"volume":90},{"name":"Decision2","pan":0,"pitch":100,"volume":90},{"name":"Cancel1","pan":0,"pitch":100,"volume":90},{"name":"Buzzer1","pan":0,"pitch":100,"volume":90},{"name":"Equip2","pan":0,"pitch":100,"volume":90},{"name":"Save","pan":0,"pitch":100,"volume":90},{"name":"Load","pan":0,"pitch":100,"volume":90},{"name":"Battle3","pan":0,"pitch":100,"volume":90},{"name":"Run","pan":0,"pitch":100,"volume":90},{"name":"Attack3","pan":0,"pitch":100,"volume":90},{"name":"Damage4","pan":0,"pitch":100,"volume":90},{"name":"Collapse3","pan":0,"pitch":100,"volume":90},{"name":"Collapse2","pan":0,"pitch":100,"volume":90},{"name":"Collapse3","pan":0,"pitch":100,"volume":90},{"name":"Damage5","pan":0,"pitch":100,"volume":90},{"name":"Collapse4","pan":0,"pitch":100,"volume":90},{"name":"Recovery","pan":0,"pitch":100,"volume":90},{"name":"Miss","pan":0,"pitch":100,"volume":90},{"name":"Evasion1","pan":0,"pitch":100,"volume":90},{"name":"Evasion2","pan":0,"pitch":100,"volume":90},{"name":"Reflection","pan":0,"pitch":100,"volume":90},{"name":"Shop1","pan":0,"pitch":100,"volume":90},{"name":"Item3","pan":0,"pitch":100,"volume":90},{"name":"Item3","pan":0,"pitch":100,"volume":90}],"startMapId":41,"startX":7,"startY":5,"switches":["","MAPfog","エロスキップON","アイテム使用禁止ON","逃走100%成功ON","釣り可能ON","釣り判定","エロ初１","必殺技使用可","陵辱イベント後制御","人間？","処女","装備変更スイッチ","人間妊娠END","エロカウンター発動","停止ＯＮ","オートバトルON","ステート変更スイッチ","断面図ON","精液塗れ","巨乳判定","Scene1登録用","Scene2登録用","Scene3登録用","Scene4登録用","Scene5登録用","Scene6登録用","Scene7登録用","Scene8登録用","Scene9登録用","Scene10登録用","Scene11登録用","Scene12登録用","Scene13登録用","Scene14登録用","Scene15登録用","Scene16登録用","Scene17登録用","Scene18登録用","Scene19登録用","Scene20登録用","Scene21登録用","Scene22登録用","Scene23登録用","Scene24登録用","Scene25登録用","Scene26登録用","Scene27登録用","Scene28登録用","Scene29登録用","Scene30登録用","Scene31登録用","Scene32登録用","Scene33登録用","Scene34登録用","Scene35登録用","Scene36登録用","Scene37登録用","Scene38登録用","Scene39登録用","Scene40登録用","Scene41登録用","Scene32登録用","","","","","","","","","","","","","","","回想用処女化","回想用巨乳化","全裸","釣り判定２","ボス１","ボス２","ボス３","","","","","","","","","","","","","","","","","","敵キャラ非発情スイッチ","敵キャラ発情スイッチ","モンフラ触手状態1","モンフラ触手状態2","初エロ攻撃被弾","モンフラ触手状態3","モンフラ触手状態4","モンフラ触手状態5","モンフラ触手状態6","モンフラ触手状態7","ＴＰチェック","モンフラ敗北1","モンフラ陵辱済ON","シラッコ敗北","シラッコ陵辱済","部下に敗北１","部下陵辱済ON","兵士隊に敗北１","ｶｰｽｽｺｰﾋﾟｵﾝ敗北","ｶｰｽｽｺｰﾋﾟｵﾝ陵辱済","ワームポット敗北","原住民に敗北","原住民に捕まる","原住民陵辱済１","原住民から脱出開始１","原住民から脱出開始２","原住民連れ戻し","脱出準備ＯＫ！","原住民１倒す","原住民２倒す","原住民３倒す","ケムリクサＧＥＴ","オークに敗北","オークに陵辱済","ワームポット陵辱済","ドロドロに敗北","ドロドロ陵辱済","トレントに敗北","トレント陵辱済","キラービに敗北","キラービー陵辱済","スライムに敗北","スライム陵辱済","ミノタウロスに敗北","ミノタウロス陵辱済","ボスロボに敗北","ボスロボ陵辱済","ビッグスパイダーに敗北","ビッグスパイダー陵辱済","ｹﾞﾙﾈｲﾂｴﾝﾃﾞｨﾝｸﾞ分岐用","触手登場1","触手登場2","触手登場3","島で自由行動開始","OPバトル用1","OPバトル用2","OPバトル用3","OPバトル用4","ゲームスタート!!","船使用可","ベーキャン１","ベーキャン２","ベーキャン３","ベーキャン４","町の遺跡１","町の遺跡２","町の遺跡３","町の遺跡４","シャワー1回目","ワームに敗北","ワーム１","ワーム２","ワーム３","ワーム４","ワーム５","ワーム６","薬草１","薬草２","薬草３","薬草４","薬草５","薬草６","薬草７","薬草８","薬草９","OPバトル敗北","薬草１０","薬草１１","オークD1","オークD2","原住民１","原住民２","原住民３","原住民４","原住民５","オークD3","オークD4","薬草１２","薬草１３","薬草１４","ボテ腹状態","おっぱい表示","淫紋表示","ボテ時淫紋表示","ラクガキ表示","触手寄生表示","触手服表示","ボテ時触手服表示","亀甲縛り表示","ボテ時亀甲縛り表示","貞操帯表示","ボテ時貞操帯表示","目隠し表示","ボールギャグ表示","母乳表示","ザーメン塗れ表示","巨乳化","巨乳+触手服","巨乳+触手服+ボテ","巨乳+亀甲","巨乳+亀甲+ボテ","巨乳+母乳","巨乳+精液","焚火の煙１ON","焚火の煙２ON","オークD5","オークD6","オークD7","オークD8","オークD9","オークD10","オーク敗北2","オークD11","オークD12","探検家１","探検家２－１","探検家２－２","探検家３","探検家４","遺跡入り口１","遺跡入り口２","遺跡入り口３","遺跡入り口４","原住民の存在認知","フラスコビーカー","部下ベースMAP","海岸洞窟MAP","オーク洞窟MAP","砂漠MAP","毒沼MAP","古代遺跡MAP","集落MAP","集落脱出後","全裸","地下1階会話終了","B1レバー説明終了","B1スイッチ１","B1スイッチ２","エアロバイク１","エアロバイク２","エアロバイク３","触手穴無事","触手穴陵辱ON1","触手穴陵辱終了１","触手穴陵辱終了２","触手穴陵辱終了３","触手穴陵辱終了４","ディルドトラップ解除","壁尻終了","壁尻終了２","遺跡のメモ","ゲルネイツ登場!!","触手穴１","触手穴２","触手穴陵辱ON2","触手穴陵辱ON3","突き落としｳｪﾌﾞﾘｰ守","突き落としｳｪﾌﾞﾘｰ奪","突き落とし悪意無し","強制ミノタウロス戦ON","ボスロボOFF","壁尻回避","ディルド罠終了","最終決戦前会話１","ゲルネイツに勝利","ワーウルフに敗北","ワーウルフ陵辱済","ミノタウロスに敗北","ミノタウロス陵辱済","ローパーに敗北","ローパー陵辱済","ゴブリンに敗北","ゴブリン陵辱済","メタルボールに敗北","メタルボール陵辱済","ボスメタルに敗北","ボスメタル陵辱済","ゲルネイツに敗北","一時停止","","ローパー１","ローパー２","ローパー３","ローパー４","ローパー５","獣の肉１","獣の肉２","獣の肉３","野鳥の肉１","野鳥の肉２","野鳥の肉３","野鳥の肉４","野鳥の肉５","ヤシの実１","ヤシの実２","バナナ１","バナナ２","バナナ３","バナナ４","薬草１５","薬草１６","薬草１７","薬草１８","薬草１９","薬草２０","薬草２１","薬草２２","クラーケン１","クラーケン２","クラーケン３","クラーケン４","クラーケン５","クラーケン６","化物イカに敗北","神殿IN","カードキーの存在ON","切りつけるOKの時","振り解くOK","暴れるOK","エロ攻撃無効化","船で脱出","エロ攻撃無効化中","ﾌﾘｰﾊﾞﾄﾙｴﾘｱ","","","","","","","","","","","","","","","","","エロ攻撃無効化"],"terms":{"basic":["等級","Lv","ＨＰ","HP","ＭＰ","MP","快感ＨＰ","快感HP","經驗值","EXP"],"commands":["戰鬥","逃跑","攻擊","不反抗","物品","技能","裝備","狀態","排序","保存","結束游戲","選項","武器","防具","負面效果","裝備","最强裝備","全部脫下","新游戲","繼續",null,"回到標題畫面","放棄",null,"購入","賣出"],"params":["最大ＨＰ","最大ＭＰ","攻擊力","防禦力","H技術","H防禦","敏捷性","運氣","命中率","閃避率"],"messages":{"actionFailure":"","actorDamage":"%1受到了 %2 的傷害！","actorDrain":"%1被%2奪走了 %3 ！","actorGain":"%1的%2增加了 %3 ！","actorLoss":"%1的%2減少了 %3 ！","actorNoDamage":"%1沒有受到傷害！","actorNoHit":"丟失！　%1沒有受到傷害！","actorRecovery":"%1的%2恢復了 %3 ！","alwaysDash":"始終衝刺","bgmVolume":"BGM 音量","bgsVolume":"BGS 音量","buffAdd":"%1的%2上升了！","buffRemove":"%1的%2恢復了原狀！","commandRemember":"指令記錄","counterAttack":"%1的反擊！","criticalToActor":"痛恨的一撃！！","criticalToEnemy":"会心一撃！！","debuffAdd":"%1的%2下降了！","defeat":"%1在戰鬥中被打敗了。","emerge":"%1出現了！","enemyDamage":"對%1造成 %2 的傷害！","enemyDrain":"奪取了%1的%2 %3 ！","enemyGain":"%1的%2增加了 %3 ！","enemyLoss":"%1的%2減少了 %3 ！","enemyNoDamage":"無法對%1造成傷害！","enemyNoHit":"丟失！　無法對%1造成傷害！","enemyRecovery":"%1的%2恢復了 %3 ！","escapeFailure":"但是無法逃走","escapeStart":"%1逃走了！","evasion":"%1躲開了攻擊！","expNext":"到下一個%1爲止","expTotal":"現在的%1","file":"文檔","levelUp":"%1的%2 上升了%3 ！","loadMessage":"加載哪個存檔？","magicEvasion":"%1消除了魔法！","magicReflection":"%1彈開了魔法！","meVolume":"ME 音量","obtainExp":"獲得了%1 的%2！","obtainGold":"獲得金幣 %1\\G ！","obtainItem":"獲得了%1！","obtainSkill":"學會了%1！","partyName":"%1們","possession":"持有數量","preemptive":"%1先發制人！","saveMessage":"保存至哪個存檔中？","seVolume":"SE 音量","substitute":"%1保護了%2！","surprise":"%1被打了個措手不及！","useItem":"%1使用了%2！","victory":"%1勝利！"}},"testBattlers":[{"actorId":1,"equips":[1,1,0,0,0],"level":1},{"actorId":2,"equips":[2,1,2,3,0],"level":1},{"actorId":3,"equips":[3,0,2,3,4],"level":1},{"actorId":4,"equips":[4,0,2,3,4],"level":1}],"testTroopId":3,"title1Name":"Title","title2Name":"","titleBgm":{"name":"ChrisSurvivalOP","pan":0,"pitch":100,"volume":90},"variables":["","クリスの現在HP","クリスの最大HP","クリスの現在TP","クリスの体感度","敵の名前取得","初体験の相手","肉奴隷判定値","","人間経験人数","魔物経験人数","出産経験回数","口内射精量","ぶっかけ量","膣内射精量","肛門射精量","身体感度Lv","口内開発Lv","フェラ","キス","精飲回数","口内絶頂回数","乳房開発Lv","乳揉み","乳首責め","パイズリ","乳首絶頂","膣内開発Lv","セックス回数","触手挿入回数","異物挿入(膣内)","膣内絶頂回数","肛門開発Lv","アナル姦","触手挿入(肛門)","異物挿入(肛門)","肛門絶頂回数","魔物経験人数","手コキ回数","足コキ回数","クリスの状態変数","開発Lvダメージ値","ステート１ダメージ倍率","ステート２ダメージ倍率","ステート３ダメージ倍率","反動SPダメージ値","乱数ダメージ値","妊娠判定乱数","クリスのMAP位置","クリスのX座標","クリスのY座標","口内開発Lv計算代入用","乳房開発Lv計算代入用","膣内開発Lv計算代入用","肛門開発Lv計算代入用","おっぱい攻撃ダメージ値","セックス攻撃ダメージ値","イラマチオ攻撃ダメージ値","母乳獲得判定ダイス","エンディング特殊判定","敗北回数","部下敗北回数","釣り乱数","エロカウンター判定","アナル攻撃ダメージ値","薬草発生乱数","乳牛ステ判定値","原住民連れ戻しカウント","体液&ガス攻撃ダメージ値","ランダムセリフ","謎解きフラグ","ローパーカウント","クリスの初期最大HP","避妊薬回数","特殊ダメージ値","立ち絵変更用変数ID","","","","","","","","","","","","","","","","","","","","","","","","",""],"versionId":46946623,"victoryMe":{"name":"Victory1","pan":0,"pitch":100,"volume":90},"weaponTypes":["","短劍","劍","虛弱","斧","鞭子","杖","弓","十字弩","槍","爪","手套","長槍"],"windowTone":[0,0,0,0],"hasEncryptedImages":true,"hasEncryptedAudio":true,"encryptionKey":"7b245dbafa1b25c30eba11c038fb899d"}